signalr_async/__init__.py
signalr_async/client.py
signalr_async/connection.py
signalr_async/exceptions.py
signalr_async/hub.py
signalr_async/invoke_manager.py
signalr_async/messages.py
signalr_async/py.typed
signalr_async/net/__init__.py
signalr_async/net/client.py
signalr_async/net/connection.py
signalr_async/net/hub.py
signalr_async/net/messages.py
signalr_async/netcore/__init__.py
signalr_async/netcore/client.py
signalr_async/netcore/connection.py
signalr_async/netcore/hub.py
signalr_async/netcore/messages.py
signalr_async/netcore/protocols/__init__.py
signalr_async/netcore/protocols/base.py
signalr_async/netcore/protocols/json.py
signalr_async/netcore/protocols/messagepack.py
signalr_client_demo-0.0.1.dist-info/licenses/LICENSE
signalr_client_demo-0.0.1.dist-info/METADATA
signalr_client_demo-0.0.1.dist-info/WHEEL
signalr_client_demo-0.0.1.dist-info/top_level.txt
signalr_client_demo-0.0.1.dist-info/RECORD
