Metadata-Version: 2.4
Name: signalr-client-demo
Version: 0.0.1
Summary: Python SignalR async client
Author-email: Sam Mosleh <sam.mosleh@ut.ac.ir>
License: MIT
Project-URL: homepage, https://github.com/sam-mosleh/signalr-async
Keywords: SignalR,SignalR client,Real-time messaging
Requires-Python: >=3.9
License-File: LICENSE
Requires-Dist: aiohttp>=3.11.16
Requires-Dist: msgpack>=1.1.0
Provides-Extra: dev
Requires-Dist: pytest>=8.3.5; extra == "dev"
Requires-Dist: pytest-cov>=6.1.0; extra == "dev"
Requires-Dist: pre-commit>=4.2.0; extra == "dev"
Requires-Dist: black>=25.1.0; extra == "dev"
Requires-Dist: isort>=6.0.1; extra == "dev"
Requires-Dist: autoflake>=2.3.1; extra == "dev"
Requires-Dist: pytest-asyncio>=0.26.0; extra == "dev"
Requires-Dist: aioresponses>=0.7.8; extra == "dev"
Requires-Dist: pytest-mock>=3.14.0; extra == "dev"
Requires-Dist: msgpack-types>=0.5.0; extra == "dev"
Requires-Dist: mypy>=1.15.0; extra == "dev"
Dynamic: license-file
